mini/generators/conj_single_feature.py
txgraffiti/__init__.py
txgraffiti/example_data/Nqubits_data.csv
txgraffiti/example_data/__init__.py
txgraffiti/example_data/calabi_yau_data.csv
txgraffiti/example_data/expressive_graph_data.csv
txgraffiti/example_data/graph_data.csv
txgraffiti/example_data/graph_data_old.csv
txgraffiti/example_data/graph_data_old2.csv
txgraffiti/example_data/integer_data.csv
txgraffiti/example_data/nba_game_data.csv
txgraffiti/example_data/polytope_data.csv
"txgraffiti/example_data/graph-edgelists/3,6_cubic_cage.txt"
txgraffiti/example_data/graph-edgelists/B_dom_B1.txt
txgraffiti/example_data/graph-edgelists/B_dom_B2.txt
txgraffiti/example_data/graph-edgelists/B_dom_B3.txt
txgraffiti/example_data/graph-edgelists/B_dom_B4.txt
txgraffiti/example_data/graph-edgelists/B_dom_B5.txt
txgraffiti/example_data/graph-edgelists/B_dom_B6.txt
txgraffiti/example_data/graph-edgelists/B_dom_B7.txt
txgraffiti/example_data/graph-edgelists/Diamond_Necklace3.txt
txgraffiti/example_data/graph-edgelists/F_2conn_example_HaHeHe.txt
txgraffiti/example_data/graph-edgelists/F_in_F_dom_HaHeHe.txt
txgraffiti/example_data/graph-edgelists/F_small_F1_HaHeHe.txt
txgraffiti/example_data/graph-edgelists/F_small_F2_HaHeHe.txt
txgraffiti/example_data/graph-edgelists/F_small_F3_HaHeHe.txt
txgraffiti/example_data/graph-edgelists/F_small_F4_HaHeHe.txt
txgraffiti/example_data/graph-edgelists/F_small_F5_HaHeHe.txt
txgraffiti/example_data/graph-edgelists/F_small_F6_HaHeHe.txt
"txgraffiti/example_data/graph-edgelists/G(18,1)-domination-core-concepts.txt"
txgraffiti/example_data/graph-edgelists/G10.txt
txgraffiti/example_data/graph-edgelists/G11.txt
txgraffiti/example_data/graph-edgelists/G12.txt
txgraffiti/example_data/graph-edgelists/G13.txt
txgraffiti/example_data/graph-edgelists/G14.txt
txgraffiti/example_data/graph-edgelists/G15.txt
txgraffiti/example_data/graph-edgelists/G16.txt
txgraffiti/example_data/graph-edgelists/G17.txt
txgraffiti/example_data/graph-edgelists/G18.txt
txgraffiti-0.4.1.dist-info/licenses/LICENSE
txgraffiti-0.4.1.dist-info/METADATA
txgraffiti-0.4.1.dist-info/WHEEL
txgraffiti-0.4.1.dist-info/top_level.txt
txgraffiti-0.4.1.dist-info/RECORD
