Metadata-Version: 2.4
Name: txgraffiti
Version: 0.4.1
Summary: A Python package for automated mathematical conjecturing
Author: Randy Davila, Jillian Eddy
License: MIT License
Project-URL: Homepage, https://github.com/RandyRDavila/txgraffiti2
Project-URL: Documentation, https://txgraffiti.readthedocs.io
Requires-Python: >=3.8
License-File: LICENSE
Requires-Dist: pandas
Requires-Dist: numpy
Requires-Dist: scipy
Requires-Dist: pulp
Requires-Dist: networkx
Requires-Dist: graphcalc
Provides-Extra: dev
Requires-Dist: pytest; extra == "dev"
Requires-Dist: pytest-cov; extra == "dev"
Requires-Dist: coverage; extra == "dev"
Requires-Dist: pandas; extra == "dev"
Requires-Dist: numpy; extra == "dev"
Requires-Dist: scipy; extra == "dev"
Requires-Dist: pulp; extra == "dev"
Requires-Dist: networkx; extra == "dev"
Requires-Dist: graphcalc; extra == "dev"
Requires-Dist: sphinx; extra == "dev"
Requires-Dist: sphinx-autodoc-typehints; extra == "dev"
Requires-Dist: myst_parser; extra == "dev"
Dynamic: license-file
